webpy_cli/cli.py
webpy_cli-1.2.dist-info/METADATA
webpy_cli-1.2.dist-info/WHEEL
webpy_cli-1.2.dist-info/entry_points.txt
webpy_cli-1.2.dist-info/top_level.txt
webpy_cli-1.2.dist-info/RECORD
