Metadata-Version: 2.1
Name: webpy-cli
Version: 1.2
Summary: CLI tool for the python WebPy Framework
Home-page: UNKNOWN
Author: Tejas Nayak
Author-email: tejasnayak25@outlook.com
License: UNKNOWN
Platform: UNKNOWN
